helloworld/__init__.py
helloworld/hello.py
test1/__init__.py
test1/test111.py
tests/__init__.py
tests/teses_1.py
tests/test_hello.py
failaowang-0.2.1.dist-info/METADATA
failaowang-0.2.1.dist-info/WHEEL
failaowang-0.2.1.dist-info/top_level.txt
failaowang-0.2.1.dist-info/RECORD
