Metadata-Version: 2.1
Name: failaowang
Version: 0.2.1
Summary: A short description of your package
Home-page: https://github.com/yourusername/your_project
Author: laowang
Author-email: 931417425@qq.com
License: MIT
Classifier: Programming Language :: Python :: 3
Classifier: License :: OSI Approved :: MIT License
Classifier: Operating System :: OS Independent
Requires-Python: >=3.6
Requires-Dist: requests
